wrf/__init__.py
wrf/_wrffortran.cpython-38-darwin.so
wrf/api.py
wrf/cache.py
wrf/computation.py
wrf/config.py
wrf/constants.py
wrf/contrib.py
wrf/coordpair.py
wrf/decorators.py
wrf/destag.py
wrf/extension.py
wrf/g_cape.py
wrf/g_cloudfrac.py
wrf/g_ctt.py
wrf/g_dbz.py
wrf/g_dewpoint.py
wrf/g_geoht.py
wrf/g_helicity.py
wrf/g_latlon.py
wrf/g_omega.py
wrf/g_precip.py
wrf/g_pressure.py
wrf/g_pw.py
wrf/g_rh.py
wrf/g_slp.py
wrf/g_temp.py
wrf/g_terrain.py
wrf/g_times.py
wrf/g_uvmet.py
wrf/g_vorticity.py
wrf/g_wind.py
wrf/geobnds.py
wrf/interp.py
wrf/interputils.py
wrf/latlonutils.py
wrf/metadecorators.py
wrf/projection.py
wrf/projutils.py
wrf/py3compat.py
wrf/routines.py
wrf/specialdec.py
wrf/units.py
wrf/util.py
wrf/version.py
wrf/data/psadilookup.dat
wrf_python-1.3.4.1.dist-info/LICENSE
wrf_python-1.3.4.1.dist-info/METADATA
wrf_python-1.3.4.1.dist-info/WHEEL
wrf_python-1.3.4.1.dist-info/top_level.txt
wrf_python-1.3.4.1.dist-info/RECORD
