Metadata-Version: 2.1
Name: wrf-python
Version: 1.3.4.1
Summary: Diagnostic and interpolation routines for WRF-ARW data.
Home-page: https://github.com/NCAR/wrf-python
Download-URL: https://python.org/pypi/wrf-python
Author: Bill Ladwig
Maintainer: GeoCAT
Maintainer-email: geocat@ucar.edu
License: Apache License 2.0
Keywords: python,wrf-python,wrf,forecast,model,weather research and forecasting,interpolation,plotting,plots,meteorology,nwp,numerical weather prediction,diagnostic,science,numpy
Platform: any
Classifier: Development Status :: 5 - Production/Stable
Classifier: Intended Audience :: Science/Research
Classifier: Intended Audience :: Developers
Classifier: License :: OSI Approved :: Apache Software License
Classifier: Programming Language :: Fortran
Classifier: Programming Language :: Python :: 3.7
Classifier: Programming Language :: Python :: 3.8
Classifier: Programming Language :: Python :: 3.9
Classifier: Topic :: Scientific/Engineering :: Atmospheric Science
Classifier: Topic :: Software Development
Classifier: Operating System :: POSIX
Classifier: Operating System :: Unix
Classifier: Operating System :: MacOS
Classifier: Operating System :: Microsoft :: Windows
Requires-Python: >=3.7
License-File: LICENSE
Requires-Dist: basemap
Requires-Dist: numpy (>=1.11)
Requires-Dist: setuptools
Requires-Dist: wrapt
Requires-Dist: xarray
